lang_search_plugin/__init__.py
lang_search_plugin/lang_search_plugin.py
lang_search_plugin-0.9.2.dist-info/LICENSE
lang_search_plugin-0.9.2.dist-info/METADATA
lang_search_plugin-0.9.2.dist-info/WHEEL
lang_search_plugin-0.9.2.dist-info/entry_points.txt
lang_search_plugin-0.9.2.dist-info/top_level.txt
lang_search_plugin-0.9.2.dist-info/RECORD
