Metadata-Version: 2.1
Name: lang_search_plugin
Version: 0.9.2
Summary: A custom language search plugin for MkDocs
Home-page: https://github.com/wdoyle123/LangSearchPlugin
Author: William Doyle
Author-email: william.e.doyle.contact@gmail.com
License: MIT
Classifier: Development Status :: 3 - Alpha
Classifier: Intended Audience :: Developers
Classifier: License :: OSI Approved :: MIT License
Classifier: Programming Language :: Python :: 3
Classifier: Programming Language :: Python :: 3.7
Classifier: Programming Language :: Python :: 3.8
Classifier: Programming Language :: Python :: 3.9
Classifier: Programming Language :: Python :: 3.10
Classifier: Programming Language :: Python :: 3.11
Classifier: Programming Language :: Python :: 3.12
License-File: LICENSE
Requires-Dist: mkdocs
Requires-Dist: beautifulsoup4
